exasol/error/__init__.py
exasol/error/__main__.py
exasol/error/_cli.py
exasol/error/_error.py
exasol/error/_error_message_builder.py
exasol/error/_exa_error.py
exasol/error/_internal_errors.py
exasol/error/_parameters_mapper.py
exasol/error/_parse.py
exasol/error/_placeholder.py
exasol/error/_placeholder_handler.py
exasol/error/_report.py
exasol/error/py.typed
exasol/error/version.py
exasol_error_reporting-1.0.0.dist-info/entry_points.txt
exasol_error_reporting-1.0.0.dist-info/LICENSE
exasol_error_reporting-1.0.0.dist-info/WHEEL
exasol_error_reporting-1.0.0.dist-info/METADATA
exasol_error_reporting-1.0.0.dist-info/RECORD
